{
  "id": "level_087",
  "starting_seeds": 99,
  "row_queue": [
    [
      {
        "col": 0,
        "kind": "totopo",
        "hp": 207
      },
      {
        "col": 1,
        "kind": "queso",
        "hp": 248
      },
      {
        "col": 2,
        "kind": "lemon"
      },
      {
        "col": 3,
        "kind": "totopo",
        "hp": 248
      },
      {
        "col": 4,
        "kind": "totopo",
        "hp": 264
      },
      {
        "col": 6,
        "kind": "totopo",
        "hp": 198
      }
    ],
    [
      {
        "col": 0,
        "kind": "totopo",
        "hp": 116
      },
      {
        "col": 1,
        "kind": "totopo",
        "hp": 160
      },
      {
        "col": 2,
        "kind": "stone"
      },
      {
        "col": 3,
        "kind": "queso",
        "hp": 375
      },
      {
        "col": 4,
        "kind": "queso",
        "hp": 182
      },
      {
        "col": 5,
        "kind": "queso",
        "hp": 140
      },
      {
        "col": 6,
        "kind": "lemon"
      }
    ],
    [
      {
        "col": 0,
        "kind": "queso",
        "hp": 332
      },
      {
        "col": 1,
        "kind": "stone"
      },
      {
        "col": 4,
        "kind": "queso",
        "hp": 270
      },
      {
        "col": 5,
        "kind": "stone"
      },
      {
        "col": 6,
        "kind": "totopo",
        "hp": 134
      }
    ],
    [
      {
        "col": 0,
        "kind": "salsa",
        "hp": 226
      },
      {
        "col": 1,
        "kind": "totopo",
        "hp": 69
      },
      {
        "col": 2,
        "kind": "totopo",
        "hp": 125
      },
      {
        "col": 4,
        "kind": "queso",
        "hp": 176
      },
      {
        "col": 5,
        "kind": "salsa",
        "hp": 179
      },
      {
        "col": 6,
        "kind": "laser",
        "orientation": "both"
      }
    ],
    [
      {
        "col": 0,
        "kind": "triangle",
        "hp": 64,
        "corner": 3
      },
      {
        "col": 1,
        "kind": "salsa",
        "hp": 140
      },
      {
        "col": 3,
        "kind": "queso",
        "hp": 174
      },
      {
        "col": 5,
        "kind": "lemon"
      },
      {
        "col": 6,
        "kind": "totopo",
        "hp": 161
      }
    ],
    [
      {
        "col": 1,
        "kind": "seed_extra"
      },
      {
        "col": 2,
        "kind": "totopo",
        "hp": 91
      },
      {
        "col": 3,
        "kind": "totopo",
        "hp": 222
      },
      {
        "col": 5,
        "kind": "totopo",
        "hp": 69
      },
      {
        "col": 6,
        "kind": "totopo",
        "hp": 173
      }
    ],
    [
      {
        "col": 0,
        "kind": "laser",
        "orientation": "horizontal"
      },
      {
        "col": 1,
        "kind": "triangle",
        "hp": 135,
        "corner": 2
      },
      {
        "col": 2,
        "kind": "salsa",
        "hp": 114
      },
      {
        "col": 3,
        "kind": "totopo",
        "hp": 170
      },
      {
        "col": 5,
        "kind": "laser",
        "orientation": "horizontal"
      },
      {
        "col": 6,
        "kind": "triangle",
        "hp": 104,
        "corner": 0
      }
    ],
    [
      {
        "col": 0,
        "kind": "seed_extra"
      },
      {
        "col": 1,
        "kind": "queso",
        "hp": 327
      },
      {
        "col": 2,
        "kind": "totopo",
        "hp": 102
      },
      {
        "col": 3,
        "kind": "totopo",
        "hp": 237
      },
      {
        "col": 4,
        "kind": "queso",
        "hp": 320
      },
      {
        "col": 5,
        "kind": "totopo",
        "hp": 78
      },
      {
        "col": 6,
        "kind": "stone"
      }
    ],
    [
      {
        "col": 0,
        "kind": "queso",
        "hp": 306
      },
      {
        "col": 3,
        "kind": "totopo",
        "hp": 141
      },
      {
        "col": 4,
        "kind": "totopo",
        "hp": 126
      },
      {
        "col": 5,
        "kind": "totopo",
        "hp": 67
      },
      {
        "col": 6,
        "kind": "salsa",
        "hp": 194
      }
    ],
    [
      {
        "col": 0,
        "kind": "queso",
        "hp": 297
      },
      {
        "col": 1,
        "kind": "totopo",
        "hp": 85
      },
      {
        "col": 2,
        "kind": "stone"
      },
      {
        "col": 3,
        "kind": "totopo",
        "hp": 86
      },
      {
        "col": 4,
        "kind": "triangle",
        "hp": 176,
        "corner": 3
      },
      {
        "col": 5,
        "kind": "triangle",
        "hp": 155,
        "corner": 0
      }
    ],
    [
      {
        "col": 0,
        "kind": "totopo",
        "hp": 54
      },
      {
        "col": 1,
        "kind": "totopo",
        "hp": 249
      },
      {
        "col": 2,
        "kind": "seed_extra"
      },
      {
        "col": 3,
        "kind": "lemon"
      },
      {
        "col": 4,
        "kind": "totopo",
        "hp": 215
      },
      {
        "col": 5,
        "kind": "stone"
      },
      {
        "col": 6,
        "kind": "totopo",
        "hp": 129
      }
    ],
    [
      {
        "col": 0,
        "kind": "stone"
      },
      {
        "col": 1,
        "kind": "totopo",
        "hp": 209
      },
      {
        "col": 2,
        "kind": "salsa",
        "hp": 175
      },
      {
        "col": 3,
        "kind": "totopo",
        "hp": 222
      },
      {
        "col": 4,
        "kind": "seed_extra"
      },
      {
        "col": 5,
        "kind": "queso",
        "hp": 147
      },
      {
        "col": 6,
        "kind": "totopo",
        "hp": 61
      }
    ],
    [
      {
        "col": 0,
        "kind": "stone"
      },
      {
        "col": 1,
        "kind": "totopo",
        "hp": 182
      },
      {
        "col": 2,
        "kind": "stone"
      },
      {
        "col": 3,
        "kind": "queso",
        "hp": 390
      },
      {
        "col": 4,
        "kind": "queso",
        "hp": 184
      },
      {
        "col": 5,
        "kind": "totopo",
        "hp": 258
      },
      {
        "col": 6,
        "kind": "triangle",
        "hp": 193,
        "corner": 2
      }
    ],
    [
      {
        "col": 0,
        "kind": "salsa",
        "hp": 62
      },
      {
        "col": 1,
        "kind": "lemon"
      },
      {
        "col": 2,
        "kind": "totopo",
        "hp": 59
      },
      {
        "col": 3,
        "kind": "totopo",
        "hp": 243
      },
      {
        "col": 4,
        "kind": "totopo",
        "hp": 82
      },
      {
        "col": 5,
        "kind": "totopo",
        "hp": 215
      },
      {
        "col": 6,
        "kind": "queso",
        "hp": 315
      }
    ],
    [
      {
        "col": 0,
        "kind": "triangle",
        "hp": 147,
        "corner": 0
      },
      {
        "col": 1,
        "kind": "totopo",
        "hp": 245
      },
      {
        "col": 2,
        "kind": "salsa",
        "hp": 170
      },
      {
        "col": 3,
        "kind": "queso",
        "hp": 204
      },
      {
        "col": 4,
        "kind": "totopo",
        "hp": 117
      },
      {
        "col": 5,
        "kind": "totopo",
        "hp": 257
      },
      {
        "col": 6,
        "kind": "totopo",
        "hp": 144
      }
    ],
    [
      {
        "col": 0,
        "kind": "totopo",
        "hp": 65
      },
      {
        "col": 1,
        "kind": "queso",
        "hp": 297
      },
      {
        "col": 4,
        "kind": "salsa",
        "hp": 53
      },
      {
        "col": 5,
        "kind": "salsa",
        "hp": 232
      },
      {
        "col": 6,
        "kind": "queso",
        "hp": 248
      }
    ],
    [
      {
        "col": 0,
        "kind": "stone"
      },
      {
        "col": 1,
        "kind": "triangle",
        "hp": 258,
        "corner": 0
      },
      {
        "col": 2,
        "kind": "queso",
        "hp": 390
      },
      {
        "col": 3,
        "kind": "totopo",
        "hp": 247
      },
      {
        "col": 4,
        "kind": "lemon"
      },
      {
        "col": 5,
        "kind": "totopo",
        "hp": 205
      },
      {
        "col": 6,
        "kind": "totopo",
        "hp": 85
      }
    ],
    [
      {
        "col": 0,
        "kind": "totopo",
        "hp": 255
      },
      {
        "col": 1,
        "kind": "stone"
      },
      {
        "col": 2,
        "kind": "totopo",
        "hp": 222
      },
      {
        "col": 3,
        "kind": "totopo",
        "hp": 174
      },
      {
        "col": 4,
        "kind": "stone"
      },
      {
        "col": 5,
        "kind": "totopo",
        "hp": 217
      },
      {
        "col": 6,
        "kind": "salsa",
        "hp": 229
      }
    ],
    [
      {
        "col": 0,
        "kind": "totopo",
        "hp": 109
      },
      {
        "col": 1,
        "kind": "totopo",
        "hp": 168
      },
      {
        "col": 2,
        "kind": "queso",
        "hp": 144
      },
      {
        "col": 3,
        "kind": "totopo",
        "hp": 257
      },
      {
        "col": 4,
        "kind": "totopo",
        "hp": 127
      },
      {
        "col": 5,
        "kind": "triangle",
        "hp": 111,
        "corner": 2
      },
      {
        "col": 6,
        "kind": "lemon"
      }
    ],
    [
      {
        "col": 0,
        "kind": "stone"
      },
      {
        "col": 1,
        "kind": "stone"
      },
      {
        "col": 2,
        "kind": "totopo",
        "hp": 236
      },
      {
        "col": 4,
        "kind": "lemon"
      },
      {
        "col": 5,
        "kind": "queso",
        "hp": 264
      },
      {
        "col": 6,
        "kind": "totopo",
        "hp": 120
      }
    ],
    [
      {
        "col": 0,
        "kind": "totopo",
        "hp": 91
      },
      {
        "col": 1,
        "kind": "queso",
        "hp": 315
      },
      {
        "col": 2,
        "kind": "totopo",
        "hp": 77
      },
      {
        "col": 3,
        "kind": "salsa",
        "hp": 164
      },
      {
        "col": 4,
        "kind": "stone"
      },
      {
        "col": 5,
        "kind": "totopo",
        "hp": 99
      },
      {
        "col": 6,
        "kind": "totopo",
        "hp": 180
      }
    ],
    [
      {
        "col": 0,
        "kind": "salsa",
        "hp": 203
      },
      {
        "col": 1,
        "kind": "triangle",
        "hp": 113,
        "corner": 1
      },
      {
        "col": 2,
        "kind": "totopo",
        "hp": 194
      },
      {
        "col": 3,
        "kind": "totopo",
        "hp": 172
      },
      {
        "col": 4,
        "kind": "totopo",
        "hp": 71
      },
      {
        "col": 5,
        "kind": "totopo",
        "hp": 62
      },
      {
        "col": 6,
        "kind": "totopo",
        "hp": 212
      }
    ],
    [
      {
        "col": 0,
        "kind": "totopo",
        "hp": 61
      },
      {
        "col": 1,
        "kind": "lemon"
      },
      {
        "col": 2,
        "kind": "totopo",
        "hp": 76
      },
      {
        "col": 3,
        "kind": "totopo",
        "hp": 230
      },
      {
        "col": 4,
        "kind": "stone"
      },
      {
        "col": 5,
        "kind": "triangle",
        "hp": 139,
        "corner": 2
      },
      {
        "col": 6,
        "kind": "queso",
        "hp": 364
      }
    ],
    [
      {
        "col": 0,
        "kind": "totopo",
        "hp": 236
      },
      {
        "col": 1,
        "kind": "seed_extra"
      },
      {
        "col": 2,
        "kind": "totopo",
        "hp": 212
      },
      {
        "col": 3,
        "kind": "queso",
        "hp": 81
      },
      {
        "col": 4,
        "kind": "lemon"
      },
      {
        "col": 5,
        "kind": "salsa",
        "hp": 77
      },
      {
        "col": 6,
        "kind": "totopo",
        "hp": 165
      }
    ],
    [
      {
        "col": 0,
        "kind": "totopo",
        "hp": 164
      },
      {
        "col": 1,
        "kind": "triangle",
        "hp": 92,
        "corner": 3
      },
      {
        "col": 2,
        "kind": "totopo",
        "hp": 130
      },
      {
        "col": 4,
        "kind": "totopo",
        "hp": 156
      },
      {
        "col": 5,
        "kind": "totopo",
        "hp": 142
      }
    ],
    [
      {
        "col": 0,
        "kind": "totopo",
        "hp": 249
      },
      {
        "col": 1,
        "kind": "queso",
        "hp": 198
      },
      {
        "col": 3,
        "kind": "queso",
        "hp": 292
      },
      {
        "col": 4,
        "kind": "laser",
        "orientation": "both"
      },
      {
        "col": 5,
        "kind": "salsa",
        "hp": 78
      },
      {
        "col": 6,
        "kind": "seed_extra"
      }
    ],
    [
      {
        "col": 0,
        "kind": "lemon"
      },
      {
        "col": 1,
        "kind": "stone"
      },
      {
        "col": 2,
        "kind": "seed_extra"
      },
      {
        "col": 3,
        "kind": "triangle",
        "hp": 103,
        "corner": 1
      },
      {
        "col": 4,
        "kind": "stone"
      },
      {
        "col": 6,
        "kind": "triangle",
        "hp": 228,
        "corner": 2
      }
    ],
    [
      {
        "col": 0,
        "kind": "totopo",
        "hp": 217
      },
      {
        "col": 1,
        "kind": "totopo",
        "hp": 76
      },
      {
        "col": 2,
        "kind": "totopo",
        "hp": 93
      },
      {
        "col": 3,
        "kind": "totopo",
        "hp": 72
      },
      {
        "col": 4,
        "kind": "laser",
        "orientation": "both"
      },
      {
        "col": 5,
        "kind": "totopo",
        "hp": 147
      },
      {
        "col": 6,
        "kind": "queso",
        "hp": 321
      }
    ],
    [
      {
        "col": 0,
        "kind": "totopo",
        "hp": 246
      },
      {
        "col": 1,
        "kind": "totopo",
        "hp": 195
      },
      {
        "col": 2,
        "kind": "totopo",
        "hp": 154
      },
      {
        "col": 4,
        "kind": "triangle",
        "hp": 101,
        "corner": 2
      },
      {
        "col": 5,
        "kind": "totopo",
        "hp": 175
      },
      {
        "col": 6,
        "kind": "totopo",
        "hp": 200
      }
    ],
    [
      {
        "col": 0,
        "kind": "totopo",
        "hp": 177
      },
      {
        "col": 1,
        "kind": "totopo",
        "hp": 193
      },
      {
        "col": 2,
        "kind": "totopo",
        "hp": 96
      },
      {
        "col": 3,
        "kind": "totopo",
        "hp": 146
      },
      {
        "col": 4,
        "kind": "totopo",
        "hp": 227
      },
      {
        "col": 5,
        "kind": "triangle",
        "hp": 266,
        "corner": 3
      }
    ],
    [
      {
        "col": 0,
        "kind": "laser",
        "orientation": "horizontal"
      },
      {
        "col": 1,
        "kind": "totopo",
        "hp": 239
      },
      {
        "col": 2,
        "kind": "salsa",
        "hp": 62
      },
      {
        "col": 3,
        "kind": "totopo",
        "hp": 190
      },
      {
        "col": 4,
        "kind": "triangle",
        "hp": 104,
        "corner": 1
      },
      {
        "col": 5,
        "kind": "totopo",
        "hp": 67
      },
      {
        "col": 6,
        "kind": "stone"
      }
    ],
    [
      {
        "col": 0,
        "kind": "seed_extra"
      },
      {
        "col": 1,
        "kind": "stone"
      },
      {
        "col": 2,
        "kind": "triangle",
        "hp": 147,
        "corner": 0
      },
      {
        "col": 3,
        "kind": "laser",
        "orientation": "vertical"
      },
      {
        "col": 4,
        "kind": "totopo",
        "hp": 195
      },
      {
        "col": 5,
        "kind": "seed_extra"
      }
    ],
    [
      {
        "col": 0,
        "kind": "totopo",
        "hp": 174
      },
      {
        "col": 1,
        "kind": "totopo",
        "hp": 176
      },
      {
        "col": 2,
        "kind": "seed_extra"
      },
      {
        "col": 3,
        "kind": "totopo",
        "hp": 151
      },
      {
        "col": 4,
        "kind": "totopo",
        "hp": 134
      },
      {
        "col": 5,
        "kind": "totopo",
        "hp": 107
      },
      {
        "col": 6,
        "kind": "totopo",
        "hp": 246
      }
    ],
    [
      {
        "col": 0,
        "kind": "lemon"
      },
      {
        "col": 1,
        "kind": "totopo",
        "hp": 228
      },
      {
        "col": 2,
        "kind": "totopo",
        "hp": 253
      },
      {
        "col": 3,
        "kind": "seed_extra"
      },
      {
        "col": 5,
        "kind": "queso",
        "hp": 153
      },
      {
        "col": 6,
        "kind": "totopo",
        "hp": 218
      }
    ],
    [
      {
        "col": 0,
        "kind": "totopo",
        "hp": 238
      },
      {
        "col": 1,
        "kind": "queso",
        "hp": 352
      },
      {
        "col": 2,
        "kind": "totopo",
        "hp": 140
      },
      {
        "col": 3,
        "kind": "totopo",
        "hp": 85
      },
      {
        "col": 4,
        "kind": "triangle",
        "hp": 206,
        "corner": 3
      },
      {
        "col": 5,
        "kind": "totopo",
        "hp": 242
      },
      {
        "col": 6,
        "kind": "queso",
        "hp": 266
      }
    ],
    [
      {
        "col": 0,
        "kind": "totopo",
        "hp": 171
      },
      {
        "col": 2,
        "kind": "totopo",
        "hp": 261
      },
      {
        "col": 4,
        "kind": "totopo",
        "hp": 108
      },
      {
        "col": 5,
        "kind": "queso",
        "hp": 96
      },
      {
        "col": 6,
        "kind": "queso",
        "hp": 278
      }
    ],
    [
      {
        "col": 0,
        "kind": "stone"
      },
      {
        "col": 3,
        "kind": "totopo",
        "hp": 248
      },
      {
        "col": 4,
        "kind": "totopo",
        "hp": 254
      },
      {
        "col": 5,
        "kind": "triangle",
        "hp": 108,
        "corner": 3
      },
      {
        "col": 6,
        "kind": "queso",
        "hp": 201
      }
    ],
    [
      {
        "col": 0,
        "kind": "totopo",
        "hp": 161
      },
      {
        "col": 1,
        "kind": "totopo",
        "hp": 153
      },
      {
        "col": 2,
        "kind": "triangle",
        "hp": 247,
        "corner": 2
      },
      {
        "col": 3,
        "kind": "lemon"
      },
      {
        "col": 4,
        "kind": "stone"
      },
      {
        "col": 5,
        "kind": "totopo",
        "hp": 115
      },
      {
        "col": 6,
        "kind": "triangle",
        "hp": 233,
        "corner": 3
      }
    ],
    [
      {
        "col": 0,
        "kind": "totopo",
        "hp": 256
      },
      {
        "col": 1,
        "kind": "totopo",
        "hp": 198
      },
      {
        "col": 2,
        "kind": "salsa",
        "hp": 237
      },
      {
        "col": 3,
        "kind": "stone"
      },
      {
        "col": 5,
        "kind": "stone"
      },
      {
        "col": 6,
        "kind": "triangle",
        "hp": 87,
        "corner": 0
      }
    ],
    [
      {
        "col": 1,
        "kind": "totopo",
        "hp": 197
      },
      {
        "col": 2,
        "kind": "totopo",
        "hp": 208
      },
      {
        "col": 3,
        "kind": "triangle",
        "hp": 69,
        "corner": 0
      },
      {
        "col": 4,
        "kind": "totopo",
        "hp": 212
      },
      {
        "col": 5,
        "kind": "triangle",
        "hp": 133,
        "corner": 1
      },
      {
        "col": 6,
        "kind": "queso",
        "hp": 106
      }
    ],
    [
      {
        "col": 0,
        "kind": "totopo",
        "hp": 116
      },
      {
        "col": 1,
        "kind": "queso",
        "hp": 284
      },
      {
        "col": 3,
        "kind": "totopo",
        "hp": 257
      },
      {
        "col": 4,
        "kind": "seed_extra"
      },
      {
        "col": 5,
        "kind": "queso",
        "hp": 286
      },
      {
        "col": 6,
        "kind": "totopo",
        "hp": 77
      }
    ],
    [
      {
        "col": 0,
        "kind": "salsa",
        "hp": 87
      },
      {
        "col": 1,
        "kind": "triangle",
        "hp": 203,
        "corner": 0
      },
      {
        "col": 2,
        "kind": "stone"
      },
      {
        "col": 3,
        "kind": "totopo",
        "hp": 53
      },
      {
        "col": 5,
        "kind": "salsa",
        "hp": 159
      },
      {
        "col": 6,
        "kind": "totopo",
        "hp": 147
      }
    ],
    [
      {
        "col": 0,
        "kind": "totopo",
        "hp": 74
      },
      {
        "col": 1,
        "kind": "queso",
        "hp": 315
      },
      {
        "col": 2,
        "kind": "totopo",
        "hp": 106
      },
      {
        "col": 3,
        "kind": "totopo",
        "hp": 103
      },
      {
        "col": 4,
        "kind": "salsa",
        "hp": 202
      },
      {
        "col": 6,
        "kind": "totopo",
        "hp": 171
      }
    ],
    [
      {
        "col": 0,
        "kind": "totopo",
        "hp": 68
      },
      {
        "col": 1,
        "kind": "totopo",
        "hp": 107
      },
      {
        "col": 2,
        "kind": "laser",
        "orientation": "horizontal"
      },
      {
        "col": 3,
        "kind": "totopo",
        "hp": 185
      },
      {
        "col": 4,
        "kind": "triangle",
        "hp": 177,
        "corner": 2
      },
      {
        "col": 5,
        "kind": "stone"
      },
      {
        "col": 6,
        "kind": "lemon"
      }
    ],
    [
      {
        "col": 0,
        "kind": "totopo",
        "hp": 163
      },
      {
        "col": 1,
        "kind": "triangle",
        "hp": 116,
        "corner": 3
      },
      {
        "col": 2,
        "kind": "seed_extra"
      },
      {
        "col": 3,
        "kind": "queso",
        "hp": 231
      },
      {
        "col": 4,
        "kind": "totopo",
        "hp": 159
      },
      {
        "col": 5,
        "kind": "laser",
        "orientation": "horizontal"
      },
      {
        "col": 6,
        "kind": "totopo",
        "hp": 216
      }
    ],
    [
      {
        "col": 0,
        "kind": "stone"
      },
      {
        "col": 1,
        "kind": "totopo",
        "hp": 138
      },
      {
        "col": 2,
        "kind": "totopo",
        "hp": 235
      },
      {
        "col": 3,
        "kind": "queso",
        "hp": 394
      },
      {
        "col": 4,
        "kind": "totopo",
        "hp": 91
      },
      {
        "col": 6,
        "kind": "totopo",
        "hp": 168
      }
    ],
    [
      {
        "col": 0,
        "kind": "totopo",
        "hp": 210
      },
      {
        "col": 1,
        "kind": "totopo",
        "hp": 255
      },
      {
        "col": 2,
        "kind": "stone"
      },
      {
        "col": 3,
        "kind": "totopo",
        "hp": 210
      },
      {
        "col": 4,
        "kind": "lemon"
      },
      {
        "col": 5,
        "kind": "salsa",
        "hp": 71
      },
      {
        "col": 6,
        "kind": "triangle",
        "hp": 122,
        "corner": 1
      }
    ],
    [
      {
        "col": 0,
        "kind": "totopo",
        "hp": 214
      },
      {
        "col": 1,
        "kind": "queso",
        "hp": 387
      },
      {
        "col": 2,
        "kind": "triangle",
        "hp": 60,
        "corner": 1
      },
      {
        "col": 3,
        "kind": "totopo",
        "hp": 96
      },
      {
        "col": 4,
        "kind": "totopo",
        "hp": 190
      },
      {
        "col": 5,
        "kind": "triangle",
        "hp": 218,
        "corner": 1
      },
      {
        "col": 6,
        "kind": "totopo",
        "hp": 248
      }
    ],
    [
      {
        "col": 0,
        "kind": "totopo",
        "hp": 73
      },
      {
        "col": 1,
        "kind": "triangle",
        "hp": 103,
        "corner": 1
      },
      {
        "col": 2,
        "kind": "totopo",
        "hp": 165
      },
      {
        "col": 3,
        "kind": "queso",
        "hp": 147
      },
      {
        "col": 5,
        "kind": "triangle",
        "hp": 164,
        "corner": 3
      },
      {
        "col": 6,
        "kind": "triangle",
        "hp": 143,
        "corner": 3
      }
    ],
    [
      {
        "col": 0,
        "kind": "stone"
      },
      {
        "col": 1,
        "kind": "totopo",
        "hp": 144
      },
      {
        "col": 2,
        "kind": "triangle",
        "hp": 174,
        "corner": 1
      },
      {
        "col": 3,
        "kind": "seed_extra"
      },
      {
        "col": 4,
        "kind": "triangle",
        "hp": 179,
        "corner": 1
      },
      {
        "col": 6,
        "kind": "stone"
      }
    ]
  ]
}