{
  "id": "worldcup_001",
  "name": "LEVEL_NAME_SOCCER_FIELD",
  "static": true,
  "grid_cols": 44,
  "starting_seeds": 50,
  "par_turns": 159,
  "cells": [
    {
      "col": 0,
      "row": 0,
      "kind": "totopo",
      "hp": 104
    },
    {
      "col": 0,
      "row": 1,
      "kind": "totopo",
      "hp": 130
    },
    {
      "col": 0,
      "row": 2,
      "kind": "totopo",
      "hp": 103
    },
    {
      "col": 0,
      "row": 3,
      "kind": "totopo",
      "hp": 245
    },
    {
      "col": 0,
      "row": 4,
      "kind": "totopo",
      "hp": 105
    },
    {
      "col": 0,
      "row": 5,
      "kind": "totopo",
      "hp": 143
    },
    {
      "col": 0,
      "row": 6,
      "kind": "totopo",
      "hp": 249
    },
    {
      "col": 0,
      "row": 7,
      "kind": "totopo",
      "hp": 94
    },
    {
      "col": 0,
      "row": 8,
      "kind": "totopo",
      "hp": 73
    },
    {
      "col": 0,
      "row": 9,
      "kind": "totopo",
      "hp": 157
    },
    {
      "col": 0,
      "row": 10,
      "kind": "totopo",
      "hp": 153
    },
    {
      "col": 0,
      "row": 11,
      "kind": "totopo",
      "hp": 199
    },
    {
      "col": 0,
      "row": 12,
      "kind": "totopo",
      "hp": 231
    },
    {
      "col": 0,
      "row": 13,
      "kind": "totopo",
      "hp": 225
    },
    {
      "col": 0,
      "row": 14,
      "kind": "totopo",
      "hp": 128
    },
    {
      "col": 0,
      "row": 15,
      "kind": "totopo",
      "hp": 253
    },
    {
      "col": 0,
      "row": 16,
      "kind": "totopo",
      "hp": 247
    },
    {
      "col": 0,
      "row": 17,
      "kind": "totopo",
      "hp": 164
    },
    {
      "col": 0,
      "row": 18,
      "kind": "totopo",
      "hp": 170
    },
    {
      "col": 0,
      "row": 19,
      "kind": "totopo",
      "hp": 158
    },
    {
      "col": 1,
      "row": 0,
      "kind": "totopo",
      "hp": 248
    },
    {
      "col": 1,
      "row": 1,
      "kind": "totopo",
      "hp": 146
    },
    {
      "col": 1,
      "row": 2,
      "kind": "totopo",
      "hp": 285
    },
    {
      "col": 1,
      "row": 4,
      "kind": "totopo",
      "hp": 152
    },
    {
      "col": 1,
      "row": 7,
      "kind": "totopo",
      "hp": 64
    },
    {
      "col": 1,
      "row": 13,
      "kind": "totopo",
      "hp": 236
    },
    {
      "col": 1,
      "row": 16,
      "kind": "totopo",
      "hp": 189
    },
    {
      "col": 1,
      "row": 17,
      "kind": "totopo",
      "hp": 238
    },
    {
      "col": 1,
      "row": 18,
      "kind": "totopo",
      "hp": 293
    },
    {
      "col": 1,
      "row": 19,
      "kind": "totopo",
      "hp": 144
    },
    {
      "col": 2,
      "row": 0,
      "kind": "totopo",
      "hp": 71
    },
    {
      "col": 2,
      "row": 1,
      "kind": "totopo",
      "hp": 130
    },
    {
      "col": 2,
      "row": 4,
      "kind": "totopo",
      "hp": 253
    },
    {
      "col": 2,
      "row": 7,
      "kind": "totopo",
      "hp": 226
    },
    {
      "col": 2,
      "row": 8,
      "kind": "totopo",
      "hp": 174
    },
    {
      "col": 2,
      "row": 9,
      "kind": "totopo",
      "hp": 211
    },
    {
      "col": 2,
      "row": 10,
      "kind": "totopo",
      "hp": 195
    },
    {
      "col": 2,
      "row": 11,
      "kind": "totopo",
      "hp": 214
    },
    {
      "col": 2,
      "row": 12,
      "kind": "totopo",
      "hp": 164
    },
    {
      "col": 2,
      "row": 13,
      "kind": "totopo",
      "hp": 128
    },
    {
      "col": 2,
      "row": 16,
      "kind": "totopo",
      "hp": 215
    },
    {
      "col": 2,
      "row": 18,
      "kind": "totopo",
      "hp": 298
    },
    {
      "col": 2,
      "row": 19,
      "kind": "totopo",
      "hp": 296
    },
    {
      "col": 3,
      "row": 0,
      "kind": "totopo",
      "hp": 85
    },
    {
      "col": 3,
      "row": 4,
      "kind": "totopo",
      "hp": 144
    },
    {
      "col": 3,
      "row": 16,
      "kind": "totopo",
      "hp": 279
    },
    {
      "col": 3,
      "row": 19,
      "kind": "totopo",
      "hp": 119
    },
    {
      "col": 4,
      "row": 0,
      "kind": "totopo",
      "hp": 223
    },
    {
      "col": 4,
      "row": 4,
      "kind": "totopo",
      "hp": 80
    },
    {
      "col": 4,
      "row": 16,
      "kind": "totopo",
      "hp": 231
    },
    {
      "col": 4,
      "row": 19,
      "kind": "totopo",
      "hp": 255
    },
    {
      "col": 5,
      "row": 0,
      "kind": "totopo",
      "hp": 278
    },
    {
      "col": 5,
      "row": 4,
      "kind": "totopo",
      "hp": 212
    },
    {
      "col": 5,
      "row": 16,
      "kind": "totopo",
      "hp": 113
    },
    {
      "col": 5,
      "row": 19,
      "kind": "totopo",
      "hp": 208
    },
    {
      "col": 6,
      "row": 0,
      "kind": "totopo",
      "hp": 246
    },
    {
      "col": 6,
      "row": 4,
      "kind": "totopo",
      "hp": 253
    },
    {
      "col": 6,
      "row": 5,
      "kind": "totopo",
      "hp": 194
    },
    {
      "col": 6,
      "row": 6,
      "kind": "totopo",
      "hp": 128
    },
    {
      "col": 6,
      "row": 7,
      "kind": "totopo",
      "hp": 66
    },
    {
      "col": 6,
      "row": 8,
      "kind": "totopo",
      "hp": 147
    },
    {
      "col": 6,
      "row": 9,
      "kind": "totopo",
      "hp": 203
    },
    {
      "col": 6,
      "row": 10,
      "kind": "totopo",
      "hp": 248
    },
    {
      "col": 6,
      "row": 11,
      "kind": "totopo",
      "hp": 290
    },
    {
      "col": 6,
      "row": 12,
      "kind": "totopo",
      "hp": 159
    },
    {
      "col": 6,
      "row": 13,
      "kind": "totopo",
      "hp": 247
    },
    {
      "col": 6,
      "row": 14,
      "kind": "totopo",
      "hp": 271
    },
    {
      "col": 6,
      "row": 15,
      "kind": "totopo",
      "hp": 162
    },
    {
      "col": 6,
      "row": 16,
      "kind": "totopo",
      "hp": 218
    },
    {
      "col": 6,
      "row": 19,
      "kind": "totopo",
      "hp": 157
    },
    {
      "col": 7,
      "row": 0,
      "kind": "totopo",
      "hp": 188
    },
    {
      "col": 7,
      "row": 19,
      "kind": "totopo",
      "hp": 189
    },
    {
      "col": 8,
      "row": 0,
      "kind": "totopo",
      "hp": 130
    },
    {
      "col": 8,
      "row": 19,
      "kind": "totopo",
      "hp": 119
    },
    {
      "col": 9,
      "row": 0,
      "kind": "totopo",
      "hp": 72
    },
    {
      "col": 9,
      "row": 19,
      "kind": "totopo",
      "hp": 229
    },
    {
      "col": 10,
      "row": 0,
      "kind": "totopo",
      "hp": 156
    },
    {
      "col": 10,
      "row": 19,
      "kind": "totopo",
      "hp": 204
    },
    {
      "col": 11,
      "row": 0,
      "kind": "totopo",
      "hp": 196
    },
    {
      "col": 11,
      "row": 19,
      "kind": "totopo",
      "hp": 111
    },
    {
      "col": 12,
      "row": 0,
      "kind": "totopo",
      "hp": 300
    },
    {
      "col": 12,
      "row": 19,
      "kind": "totopo",
      "hp": 72
    },
    {
      "col": 13,
      "row": 0,
      "kind": "totopo",
      "hp": 207
    },
    {
      "col": 13,
      "row": 19,
      "kind": "totopo",
      "hp": 203
    },
    {
      "col": 14,
      "row": 0,
      "kind": "totopo",
      "hp": 167
    },
    {
      "col": 14,
      "row": 19,
      "kind": "totopo",
      "hp": 136
    },
    {
      "col": 15,
      "row": 0,
      "kind": "totopo",
      "hp": 171
    },
    {
      "col": 15,
      "row": 10,
      "kind": "totopo",
      "hp": 69
    },
    {
      "col": 15,
      "row": 19,
      "kind": "totopo",
      "hp": 272
    },
    {
      "col": 16,
      "row": 0,
      "kind": "totopo",
      "hp": 82
    },
    {
      "col": 16,
      "row": 7,
      "kind": "totopo",
      "hp": 187
    },
    {
      "col": 16,
      "row": 8,
      "kind": "totopo",
      "hp": 150
    },
    {
      "col": 16,
      "row": 9,
      "kind": "totopo",
      "hp": 115
    },
    {
      "col": 16,
      "row": 10,
      "kind": "totopo",
      "hp": 238
    },
    {
      "col": 16,
      "row": 11,
      "kind": "totopo",
      "hp": 267
    },
    {
      "col": 16,
      "row": 12,
      "kind": "totopo",
      "hp": 219
    },
    {
      "col": 16,
      "row": 13,
      "kind": "totopo",
      "hp": 278
    },
    {
      "col": 16,
      "row": 19,
      "kind": "totopo",
      "hp": 267
    },
    {
      "col": 17,
      "row": 0,
      "kind": "totopo",
      "hp": 63
    },
    {
      "col": 17,
      "row": 6,
      "kind": "totopo",
      "hp": 259
    },
    {
      "col": 17,
      "row": 7,
      "kind": "totopo",
      "hp": 215
    },
    {
      "col": 17,
      "row": 13,
      "kind": "totopo",
      "hp": 184
    },
    {
      "col": 17,
      "row": 14,
      "kind": "totopo",
      "hp": 189
    },
    {
      "col": 17,
      "row": 19,
      "kind": "totopo",
      "hp": 159
    },
    {
      "col": 18,
      "row": 0,
      "kind": "totopo",
      "hp": 85
    },
    {
      "col": 18,
      "row": 5,
      "kind": "totopo",
      "hp": 147
    },
    {
      "col": 18,
      "row": 15,
      "kind": "totopo",
      "hp": 259
    },
    {
      "col": 18,
      "row": 19,
      "kind": "totopo",
      "hp": 160
    },
    {
      "col": 19,
      "row": 0,
      "kind": "totopo",
      "hp": 157
    },
    {
      "col": 19,
      "row": 4,
      "kind": "totopo",
      "hp": 147
    },
    {
      "col": 19,
      "row": 5,
      "kind": "totopo",
      "hp": 247
    },
    {
      "col": 19,
      "row": 15,
      "kind": "totopo",
      "hp": 119
    },
    {
      "col": 19,
      "row": 16,
      "kind": "totopo",
      "hp": 196
    },
    {
      "col": 19,
      "row": 19,
      "kind": "totopo",
      "hp": 263
    },
    {
      "col": 20,
      "row": 0,
      "kind": "totopo",
      "hp": 217
    },
    {
      "col": 20,
      "row": 4,
      "kind": "totopo",
      "hp": 159
    },
    {
      "col": 20,
      "row": 16,
      "kind": "totopo",
      "hp": 104
    },
    {
      "col": 20,
      "row": 19,
      "kind": "totopo",
      "hp": 89
    },
    {
      "col": 21,
      "row": 0,
      "kind": "totopo",
      "hp": 148
    },
    {
      "col": 21,
      "row": 4,
      "kind": "totopo",
      "hp": 190
    },
    {
      "col": 21,
      "row": 16,
      "kind": "totopo",
      "hp": 294
    },
    {
      "col": 21,
      "row": 19,
      "kind": "totopo",
      "hp": 286
    },
    {
      "col": 22,
      "row": 0,
      "kind": "totopo",
      "hp": 191
    },
    {
      "col": 22,
      "row": 1,
      "kind": "totopo",
      "hp": 225
    },
    {
      "col": 22,
      "row": 2,
      "kind": "totopo",
      "hp": 118
    },
    {
      "col": 22,
      "row": 3,
      "kind": "totopo",
      "hp": 82
    },
    {
      "col": 22,
      "row": 4,
      "kind": "totopo",
      "hp": 212
    },
    {
      "col": 22,
      "row": 5,
      "kind": "totopo",
      "hp": 72
    },
    {
      "col": 22,
      "row": 6,
      "kind": "totopo",
      "hp": 271
    },
    {
      "col": 22,
      "row": 7,
      "kind": "totopo",
      "hp": 88
    },
    {
      "col": 22,
      "row": 8,
      "kind": "totopo",
      "hp": 116
    },
    {
      "col": 22,
      "row": 9,
      "kind": "totopo",
      "hp": 63
    },
    {
      "col": 22,
      "row": 10,
      "kind": "totopo",
      "hp": 129
    },
    {
      "col": 22,
      "row": 11,
      "kind": "totopo",
      "hp": 164
    },
    {
      "col": 22,
      "row": 12,
      "kind": "totopo",
      "hp": 162
    },
    {
      "col": 22,
      "row": 13,
      "kind": "totopo",
      "hp": 288
    },
    {
      "col": 22,
      "row": 14,
      "kind": "totopo",
      "hp": 274
    },
    {
      "col": 22,
      "row": 15,
      "kind": "totopo",
      "hp": 97
    },
    {
      "col": 22,
      "row": 16,
      "kind": "totopo",
      "hp": 77
    },
    {
      "col": 22,
      "row": 17,
      "kind": "totopo",
      "hp": 98
    },
    {
      "col": 22,
      "row": 18,
      "kind": "totopo",
      "hp": 201
    },
    {
      "col": 22,
      "row": 19,
      "kind": "totopo",
      "hp": 114
    },
    {
      "col": 23,
      "row": 0,
      "kind": "totopo",
      "hp": 61
    },
    {
      "col": 23,
      "row": 4,
      "kind": "totopo",
      "hp": 289
    },
    {
      "col": 23,
      "row": 16,
      "kind": "totopo",
      "hp": 117
    },
    {
      "col": 23,
      "row": 19,
      "kind": "totopo",
      "hp": 122
    },
    {
      "col": 24,
      "row": 0,
      "kind": "totopo",
      "hp": 166
    },
    {
      "col": 24,
      "row": 4,
      "kind": "totopo",
      "hp": 234
    },
    {
      "col": 24,
      "row": 16,
      "kind": "totopo",
      "hp": 224
    },
    {
      "col": 24,
      "row": 19,
      "kind": "totopo",
      "hp": 167
    },
    {
      "col": 25,
      "row": 0,
      "kind": "totopo",
      "hp": 282
    },
    {
      "col": 25,
      "row": 4,
      "kind": "totopo",
      "hp": 270
    },
    {
      "col": 25,
      "row": 5,
      "kind": "totopo",
      "hp": 239
    },
    {
      "col": 25,
      "row": 15,
      "kind": "totopo",
      "hp": 208
    },
    {
      "col": 25,
      "row": 16,
      "kind": "totopo",
      "hp": 114
    },
    {
      "col": 25,
      "row": 19,
      "kind": "totopo",
      "hp": 216
    },
    {
      "col": 26,
      "row": 0,
      "kind": "totopo",
      "hp": 183
    },
    {
      "col": 26,
      "row": 5,
      "kind": "totopo",
      "hp": 173
    },
    {
      "col": 26,
      "row": 15,
      "kind": "totopo",
      "hp": 166
    },
    {
      "col": 26,
      "row": 19,
      "kind": "totopo",
      "hp": 188
    },
    {
      "col": 27,
      "row": 0,
      "kind": "totopo",
      "hp": 141
    },
    {
      "col": 27,
      "row": 6,
      "kind": "totopo",
      "hp": 209
    },
    {
      "col": 27,
      "row": 7,
      "kind": "totopo",
      "hp": 76
    },
    {
      "col": 27,
      "row": 13,
      "kind": "totopo",
      "hp": 181
    },
    {
      "col": 27,
      "row": 14,
      "kind": "totopo",
      "hp": 236
    },
    {
      "col": 27,
      "row": 19,
      "kind": "totopo",
      "hp": 202
    },
    {
      "col": 28,
      "row": 0,
      "kind": "totopo",
      "hp": 219
    },
    {
      "col": 28,
      "row": 7,
      "kind": "totopo",
      "hp": 254
    },
    {
      "col": 28,
      "row": 8,
      "kind": "totopo",
      "hp": 111
    },
    {
      "col": 28,
      "row": 9,
      "kind": "totopo",
      "hp": 118
    },
    {
      "col": 28,
      "row": 10,
      "kind": "totopo",
      "hp": 180
    },
    {
      "col": 28,
      "row": 11,
      "kind": "totopo",
      "hp": 251
    },
    {
      "col": 28,
      "row": 12,
      "kind": "totopo",
      "hp": 255
    },
    {
      "col": 28,
      "row": 13,
      "kind": "totopo",
      "hp": 152
    },
    {
      "col": 28,
      "row": 19,
      "kind": "totopo",
      "hp": 139
    },
    {
      "col": 29,
      "row": 0,
      "kind": "totopo",
      "hp": 178
    },
    {
      "col": 29,
      "row": 10,
      "kind": "totopo",
      "hp": 143
    },
    {
      "col": 29,
      "row": 19,
      "kind": "totopo",
      "hp": 115
    },
    {
      "col": 30,
      "row": 0,
      "kind": "totopo",
      "hp": 75
    },
    {
      "col": 30,
      "row": 19,
      "kind": "totopo",
      "hp": 280
    },
    {
      "col": 31,
      "row": 0,
      "kind": "totopo",
      "hp": 281
    },
    {
      "col": 31,
      "row": 19,
      "kind": "totopo",
      "hp": 203
    },
    {
      "col": 32,
      "row": 0,
      "kind": "totopo",
      "hp": 187
    },
    {
      "col": 32,
      "row": 19,
      "kind": "totopo",
      "hp": 124
    },
    {
      "col": 33,
      "row": 0,
      "kind": "totopo",
      "hp": 271
    },
    {
      "col": 33,
      "row": 19,
      "kind": "totopo",
      "hp": 165
    },
    {
      "col": 34,
      "row": 0,
      "kind": "totopo",
      "hp": 111
    },
    {
      "col": 34,
      "row": 19,
      "kind": "totopo",
      "hp": 190
    },
    {
      "col": 35,
      "row": 0,
      "kind": "totopo",
      "hp": 199
    },
    {
      "col": 35,
      "row": 19,
      "kind": "totopo",
      "hp": 177
    },
    {
      "col": 36,
      "row": 0,
      "kind": "totopo",
      "hp": 241
    },
    {
      "col": 36,
      "row": 19,
      "kind": "totopo",
      "hp": 239
    },
    {
      "col": 37,
      "row": 0,
      "kind": "totopo",
      "hp": 158
    },
    {
      "col": 37,
      "row": 4,
      "kind": "totopo",
      "hp": 298
    },
    {
      "col": 37,
      "row": 5,
      "kind": "totopo",
      "hp": 117
    },
    {
      "col": 37,
      "row": 6,
      "kind": "totopo",
      "hp": 66
    },
    {
      "col": 37,
      "row": 7,
      "kind": "totopo",
      "hp": 282
    },
    {
      "col": 37,
      "row": 8,
      "kind": "totopo",
      "hp": 168
    },
    {
      "col": 37,
      "row": 9,
      "kind": "totopo",
      "hp": 143
    },
    {
      "col": 37,
      "row": 10,
      "kind": "totopo",
      "hp": 159
    },
    {
      "col": 37,
      "row": 11,
      "kind": "totopo",
      "hp": 262
    },
    {
      "col": 37,
      "row": 12,
      "kind": "totopo",
      "hp": 84
    },
    {
      "col": 37,
      "row": 13,
      "kind": "totopo",
      "hp": 242
    },
    {
      "col": 37,
      "row": 14,
      "kind": "totopo",
      "hp": 296
    },
    {
      "col": 37,
      "row": 15,
      "kind": "totopo",
      "hp": 255
    },
    {
      "col": 37,
      "row": 16,
      "kind": "totopo",
      "hp": 192
    },
    {
      "col": 37,
      "row": 19,
      "kind": "totopo",
      "hp": 213
    },
    {
      "col": 38,
      "row": 0,
      "kind": "totopo",
      "hp": 178
    },
    {
      "col": 38,
      "row": 4,
      "kind": "totopo",
      "hp": 108
    },
    {
      "col": 38,
      "row": 16,
      "kind": "totopo",
      "hp": 203
    },
    {
      "col": 38,
      "row": 19,
      "kind": "totopo",
      "hp": 180
    },
    {
      "col": 39,
      "row": 0,
      "kind": "totopo",
      "hp": 221
    },
    {
      "col": 39,
      "row": 4,
      "kind": "totopo",
      "hp": 65
    },
    {
      "col": 39,
      "row": 16,
      "kind": "totopo",
      "hp": 152
    },
    {
      "col": 39,
      "row": 19,
      "kind": "totopo",
      "hp": 221
    },
    {
      "col": 40,
      "row": 0,
      "kind": "totopo",
      "hp": 158
    },
    {
      "col": 40,
      "row": 4,
      "kind": "totopo",
      "hp": 296
    },
    {
      "col": 40,
      "row": 16,
      "kind": "totopo",
      "hp": 147
    },
    {
      "col": 40,
      "row": 19,
      "kind": "totopo",
      "hp": 95
    },
    {
      "col": 41,
      "row": 0,
      "kind": "totopo",
      "hp": 131
    },
    {
      "col": 41,
      "row": 1,
      "kind": "totopo",
      "hp": 109
    },
    {
      "col": 41,
      "row": 4,
      "kind": "totopo",
      "hp": 270
    },
    {
      "col": 41,
      "row": 7,
      "kind": "totopo",
      "hp": 106
    },
    {
      "col": 41,
      "row": 8,
      "kind": "totopo",
      "hp": 274
    },
    {
      "col": 41,
      "row": 9,
      "kind": "totopo",
      "hp": 103
    },
    {
      "col": 41,
      "row": 10,
      "kind": "totopo",
      "hp": 262
    },
    {
      "col": 41,
      "row": 11,
      "kind": "totopo",
      "hp": 286
    },
    {
      "col": 41,
      "row": 12,
      "kind": "totopo",
      "hp": 71
    },
    {
      "col": 41,
      "row": 13,
      "kind": "totopo",
      "hp": 62
    },
    {
      "col": 41,
      "row": 16,
      "kind": "totopo",
      "hp": 245
    },
    {
      "col": 41,
      "row": 18,
      "kind": "totopo",
      "hp": 276
    },
    {
      "col": 41,
      "row": 19,
      "kind": "totopo",
      "hp": 233
    },
    {
      "col": 42,
      "row": 0,
      "kind": "totopo",
      "hp": 254
    },
    {
      "col": 42,
      "row": 1,
      "kind": "totopo",
      "hp": 125
    },
    {
      "col": 42,
      "row": 2,
      "kind": "totopo",
      "hp": 157
    },
    {
      "col": 42,
      "row": 4,
      "kind": "totopo",
      "hp": 285
    },
    {
      "col": 42,
      "row": 7,
      "kind": "totopo",
      "hp": 110
    },
    {
      "col": 42,
      "row": 13,
      "kind": "totopo",
      "hp": 110
    },
    {
      "col": 42,
      "row": 16,
      "kind": "totopo",
      "hp": 208
    },
    {
      "col": 42,
      "row": 17,
      "kind": "totopo",
      "hp": 95
    },
    {
      "col": 42,
      "row": 18,
      "kind": "totopo",
      "hp": 158
    },
    {
      "col": 42,
      "row": 19,
      "kind": "totopo",
      "hp": 209
    },
    {
      "col": 43,
      "row": 0,
      "kind": "totopo",
      "hp": 254
    },
    {
      "col": 43,
      "row": 1,
      "kind": "totopo",
      "hp": 281
    },
    {
      "col": 43,
      "row": 2,
      "kind": "totopo",
      "hp": 285
    },
    {
      "col": 43,
      "row": 3,
      "kind": "totopo",
      "hp": 138
    },
    {
      "col": 43,
      "row": 4,
      "kind": "totopo",
      "hp": 94
    },
    {
      "col": 43,
      "row": 5,
      "kind": "totopo",
      "hp": 284
    },
    {
      "col": 43,
      "row": 6,
      "kind": "totopo",
      "hp": 209
    },
    {
      "col": 43,
      "row": 7,
      "kind": "totopo",
      "hp": 171
    },
    {
      "col": 43,
      "row": 8,
      "kind": "totopo",
      "hp": 149
    },
    {
      "col": 43,
      "row": 9,
      "kind": "totopo",
      "hp": 236
    },
    {
      "col": 43,
      "row": 10,
      "kind": "totopo",
      "hp": 111
    },
    {
      "col": 43,
      "row": 11,
      "kind": "totopo",
      "hp": 123
    },
    {
      "col": 43,
      "row": 12,
      "kind": "totopo",
      "hp": 74
    },
    {
      "col": 43,
      "row": 13,
      "kind": "totopo",
      "hp": 106
    },
    {
      "col": 43,
      "row": 14,
      "kind": "totopo",
      "hp": 169
    },
    {
      "col": 43,
      "row": 15,
      "kind": "totopo",
      "hp": 146
    },
    {
      "col": 43,
      "row": 16,
      "kind": "totopo",
      "hp": 132
    },
    {
      "col": 43,
      "row": 17,
      "kind": "totopo",
      "hp": 108
    },
    {
      "col": 43,
      "row": 18,
      "kind": "totopo",
      "hp": 258
    },
    {
      "col": 43,
      "row": 19,
      "kind": "totopo",
      "hp": 180
    },
    {
      "col": 26,
      "row": 8,
      "kind": "lemon"
    },
    {
      "col": 41,
      "row": 3,
      "kind": "seed_extra"
    },
    {
      "col": 13,
      "row": 3,
      "kind": "seed_extra"
    },
    {
      "col": 15,
      "row": 11,
      "kind": "laser",
      "orientation": "vertical"
    },
    {
      "col": 32,
      "row": 6,
      "kind": "lemon"
    },
    {
      "col": 35,
      "row": 13,
      "kind": "seed_extra"
    },
    {
      "col": 30,
      "row": 3,
      "kind": "seed_extra"
    },
    {
      "col": 17,
      "row": 10,
      "kind": "laser",
      "orientation": "horizontal"
    },
    {
      "col": 4,
      "row": 18,
      "kind": "lemon"
    },
    {
      "col": 24,
      "row": 15,
      "kind": "seed_extra"
    },
    {
      "col": 9,
      "row": 17,
      "kind": "seed_extra"
    },
    {
      "col": 13,
      "row": 7,
      "kind": "laser",
      "orientation": "horizontal"
    },
    {
      "col": 40,
      "row": 9,
      "kind": "lemon"
    },
    {
      "col": 14,
      "row": 15,
      "kind": "seed_extra"
    },
    {
      "col": 33,
      "row": 16,
      "kind": "seed_extra"
    },
    {
      "col": 42,
      "row": 10,
      "kind": "laser",
      "orientation": "horizontal"
    },
    {
      "col": 9,
      "row": 8,
      "kind": "lemon"
    },
    {
      "col": 20,
      "row": 8,
      "kind": "seed_extra"
    }
  ]
}